.coverage
.editorconfig
.gitignore
.travis.yml
CHANGELOG.rst
LICENSE
MANIFEST.in
Makefile
README.rst
coverage.xml
requirements-test.txt
requirements.txt
setup.cfg
setup.py
docs/Makefile
docs/api.rst
docs/changelog.rst
docs/conf.py
docs/index.rst
docs/make.bat
opentracing/__init__.py
opentracing/logs.py
opentracing/propagation.py
opentracing/scope.py
opentracing/scope_manager.py
opentracing/span.py
opentracing/tags.py
opentracing/tracer.py
opentracing.egg-info/PKG-INFO
opentracing.egg-info/SOURCES.txt
opentracing.egg-info/dependency_links.txt
opentracing.egg-info/not-zip-safe
opentracing.egg-info/requires.txt
opentracing.egg-info/top_level.txt
opentracing/ext/__init__.py
opentracing/ext/tags.py
opentracing/harness/__init__.py
opentracing/harness/api_check.py
opentracing/harness/scope_check.py
opentracing/mocktracer/__init__.py
opentracing/mocktracer/binary_propagator.py
opentracing/mocktracer/context.py
opentracing/mocktracer/propagator.py
opentracing/mocktracer/span.py
opentracing/mocktracer/text_propagator.py
opentracing/mocktracer/tracer.py
opentracing/scope_managers/__init__.py
opentracing/scope_managers/asyncio.py
opentracing/scope_managers/constants.py
opentracing/scope_managers/gevent.py
opentracing/scope_managers/tornado.py
tests/__init__.py
tests/conftest.py
tests/test_api.py
tests/test_api_check_mixin.py
tests/test_globaltracer.py
tests/test_noop_span.py
tests/test_noop_tracer.py
tests/test_scope.py
tests/test_scope_check_mixin.py
tests/test_scope_manager.py
tests/ext/__init__.py
tests/mocktracer/__init__.py
tests/mocktracer/test_api.py
tests/mocktracer/test_propagation.py
tests/mocktracer/test_span.py
tests/mocktracer/test_tracer.py
tests/scope_managers/__init__.py
tests/scope_managers/test_asyncio.py
tests/scope_managers/test_gevent.py
tests/scope_managers/test_threadlocal.py
tests/scope_managers/test_tornado.py