Metadata-Version: 2.1
Name: opentracing
Version: 2.1.0
Summary: OpenTracing API for Python. See documentation at http://opentracing.io
Home-page: https://github.com/opentracing/opentracing-python
Author: The OpenTracing Authors
Author-email: opentracing@googlegroups.com
License: Apache License 2.0
Keywords: opentracing
Platform: any
Classifier: Development Status :: 5 - Production/Stable
Classifier: Intended Audience :: Developers
Classifier: License :: OSI Approved :: Apache Software License
Classifier: Programming Language :: Python :: 2.7
Classifier: Programming Language :: Python :: 3.6
Classifier: Programming Language :: Python :: Implementation :: PyPy
Classifier: Topic :: Software Development :: Libraries :: Python Modules
Provides-Extra: tests
